Workbook

Sheet 9EXPERT-VLOOKUP(9EXPERT ORDERS)
A1: OrderID | B1: OrderDate | C1: CustomerID | D1: Customer | E1: Phone | F1: ProductID | G1: Product | H1: UnitInStocks | I1: Quantity | J1: Cost | K1: UnitPrice | L1: Discount
A2: 17001 | B2: 1/1/2023 | C2: 10EXPERT | D2: =_xlfn.XLOOKUP(_9EXPERT_VLOOKUP_9EXPERT_ORDERS[[#This Row],[CustomerID]],'(CUSTOMERS)'!A:A,'(CUSTOMERS)'!B:B,"") | E2: =_xlfn.XLOOKUP(_9EXPERT_VLOOKUP_9EXPERT_ORDERS[[#This Row],[Customer]],'(CUSTOMERS)'!B:B,'(CUSTOMERS)'!G:G,"") | F2: 4-112345 | G2: =_xlfn.XLOOKUP(_9EXPERT_VLOOKUP_9EXPERT_ORDERS[[#This Row],[ProductID]],'(PRODUCTS)'!A:A,'(PRODUCTS)'!B:B,"") | H2: =_xlfn.XLOOKUP(_9EXPERT_VLOOKUP_9EXPERT_ORDERS[[#This Row],[Product]],'(PRODUCTS)'!B:B,'(PRODUCTS)'!F:F,"") | I2: 12 | J2: 10.25 | K2: 14 | L2: 0.1
A3: 17001 | B3: 1/1/2023 | C3: 9EXPERT | D3: =_xlfn.XLOOKUP(_9EXPERT_VLOOKUP_9EXPERT_ORDERS[[#This Row],[CustomerID]],'(CUSTOMERS)'!A:A,'(CUSTOMERS)'!B:B,"") -> 9Expert Co., Ltd. | E3: =_xlfn.XLOOKUP(_9EXPERT_VLOOKUP_9EXPERT_ORDERS[[#This Row],[Customer]],'(CUSTOMERS)'!B:B,'(CUSTOMERS)'!G:G,"") -> 022194304 | F3: 4-168 | G3: =_xlfn.XLOOKUP(_9EXPERT_VLOOKUP_9EXPERT_ORDERS[[#This Row],[ProductID]],'(PRODUCTS)'!A:A,'(PRODUCTS)'!B:B,"") -> Mozzarella di Giovanni | H3: =_xlfn.XLOOKUP(_9EXPERT_VLOOKUP_9EXPERT_ORDERS[[#This Row],[Product]],'(PRODUCTS)'!B:B,'(PRODUCTS)'!F:F,"") -> 14 | I3: 5 | J3: 17.54 | K3: 34.8 | L3: 0.1
A4: 17001 | B4: 1/1/2023 | C4: 9EXPERT | D4: =_xlfn.XLOOKUP(_9EXPERT_VLOOKUP_9EXPERT_ORDERS[[#This Row],[CustomerID]],'(CUSTOMERS)'!A:A,'(CUSTOMERS)'!B:B,"") -> 9Expert Co., Ltd. | E4: =_xlfn.XLOOKUP(_9EXPERT_VLOOKUP_9EXPERT_ORDERS[[#This Row],[Customer]],'(CUSTOMERS)'!B:B,'(CUSTOMERS)'!G:G,"") -> 022194304 | F4: 5-159 | G4: =_xlfn.XLOOKUP(_9EXPERT_VLOOKUP_9EXPERT_ORDERS[[#This Row],[ProductID]],'(PRODUCTS)'!A:A,'(PRODUCTS)'!B:B,"") -> Singaporean Hokkien Fried | H4: =_xlfn.XLOOKUP(_9EXPERT_VLOOKUP_9EXPERT_ORDERS[[#This Row],[Product]],'(PRODUCTS)'!B:B,'(PRODUCTS)'!F:F,"") -> 26 | I4: 10 | J4: 7.73 | K4: 9.8 | L4: 0.1
A5: 17002 | B5: 1/2/2023 | C5: TOMSP | D5: =_xlfn.XLOOKUP(_9EXPERT_VLOOKUP_9EXPERT_ORDERS[[#This Row],[CustomerID]],'(CUSTOMERS)'!A:A,'(CUSTOMERS)'!B:B,"") -> Toms Spezialitไten | E5: =_xlfn.XLOOKUP(_9EXPERT_VLOOKUP_9EXPERT_ORDERS[[#This Row],[Customer]],'(CUSTOMERS)'!B:B,'(CUSTOMERS)'!G:G,"") -> 0251-031259 | F5: 1-136 | G5: =_xlfn.XLOOKUP(_9EXPERT_VLOOKUP_9EXPERT_ORDERS[[#This Row],[ProductID]],'(PRODUCTS)'!A:A,'(PRODUCTS)'!B:B,"") -> C๔tes de Blaye | H5: =_xlfn.XLOOKUP(_9EXPERT_VLOOKUP_9EXPERT_ORDERS[[#This Row],[Product]],'(PRODUCTS)'!B:B,'(PRODUCTS)'!F:F,"") -> 17 | I5: 35 | J5: 100.5 | K5: 175 | L5: 0.05
A6: 17002 | B6: 1/2/2023 | C6: TOMSP | D6: =_xlfn.XLOOKUP(_9EXPERT_VLOOKUP_9EXPERT_ORDERS[[#This Row],[CustomerID]],'(CUSTOMERS)'!A:A,'(CUSTOMERS)'!B:B,"") -> Toms Spezialitไten | E6: =_xlfn.XLOOKUP(_9EXPERT_VLOOKUP_9EXPERT_ORDERS[[#This Row],[Customer]],'(CUSTOMERS)'!B:B,'(CUSTOMERS)'!G:G,"") -> 0251-031259 | F6: 7-125 | G6: =_xlfn.XLOOKUP(_9EXPERT_VLOOKUP_9EXPERT_ORDERS[[#This Row],[ProductID]],'(PRODUCTS)'!A:A,'(PRODUCTS)'!B:B,"") -> Tofu | H6: =_xlfn.XLOOKUP(_9EXPERT_VLOOKUP_9EXPERT_ORDERS[[#This Row],[Product]],'(PRODUCTS)'!B:B,'(PRODUCTS)'!F:F,"") -> 35 | I6: 9 | J6: 14.65 | K6: 18.6 | L6: 0
A7: 17002 | B7: 1/2/2023 | C7: TOMSP | D7: =_xlfn.XLOOKUP(_9EXPERT_VLOOKUP_9EXPERT_ORDERS[[#This Row],[CustomerID]],'(CUSTOMERS)'!A:A,'(CUSTOMERS)'!B:B,"") -> Toms Spezialitไten | E7: =_xlfn.XLOOKUP(_9EXPERT_VLOOKUP_9EXPERT_ORDERS[[#This Row],[Customer]],'(CUSTOMERS)'!B:B,'(CUSTOMERS)'!G:G,"") -> 0251-031259 | F7: 7-159 | G7: =_xlfn.XLOOKUP(_9EXPERT_VLOOKUP_9EXPERT_ORDERS[[#This Row],[ProductID]],'(PRODUCTS)'!A:A,'(PRODUCTS)'!B:B,"") -> Manjimup Dried Apples | H7: =_xlfn.XLOOKUP(_9EXPERT_VLOOKUP_9EXPERT_ORDERS[[#This Row],[Product]],'(PRODUCTS)'!B:B,'(PRODUCTS)'!F:F,"") -> 20 | I7: 25 | J7: 28.83 | K7: 42.4 | L7: 0
A8: 17003 | B8: 1/5/2023 | C8: HANAR | D8: =_xlfn.XLOOKUP(_9EXPERT_VLOOKUP_9EXPERT_ORDERS[[#This Row],[CustomerID]],'(CUSTOMERS)'!A:A,'(CUSTOMERS)'!B:B,"") -> Hanari Carnes | E8: =_xlfn.XLOOKUP(_9EXPERT_VLOOKUP_9EXPERT_ORDERS[[#This Row],[Customer]],'(CUSTOMERS)'!B:B,'(CUSTOMERS)'!G:G,"") -> (21) 555-0091 | F8: 2-125 | G8: =_xlfn.XLOOKUP(_9EXPERT_VLOOKUP_9EXPERT_ORDERS[[#This Row],[ProductID]],'(PRODUCTS)'!A:A,'(PRODUCTS)'!B:B,"") -> Louisiana Fiery Hot Pepper Sauce | H8: =_xlfn.XLOOKUP(_9EXPERT_VLOOKUP_9EXPERT_ORDERS[[#This Row],[Product]],'(PRODUCTS)'!B:B,'(PRODUCTS)'!F:F,"") -> 76 | I8: 15 | J8: 12.8 | K8: 16.8 | L8: 0.15
A9: 17003 | B9: 1/5/2023 | C9: HANAR | D9: =_xlfn.XLOOKUP(_9EXPERT_VLOOKUP_9EXPERT_ORDERS[[#This Row],[CustomerID]],'(CUSTOMERS)'!A:A,'(CUSTOMERS)'!B:B,"") -> Hanari Carnes | E9: =_xlfn.XLOOKUP(_9EXPERT_VLOOKUP_9EXPERT_ORDERS[[#This Row],[Customer]],'(CUSTOMERS)'!B:B,'(CUSTOMERS)'!G:G,"") -> (21) 555-0091 | F9: 7-159 | G9: =_xlfn.XLOOKUP(_9EXPERT_VLOOKUP_9EXPERT_ORDERS[[#This Row],[ProductID]],'(PRODUCTS)'!A:A,'(PRODUCTS)'!B:B,"") -> Manjimup Dried Apples | H9: =_xlfn.XLOOKUP(_9EXPERT_VLOOKUP_9EXPERT_ORDERS[[#This Row],[Product]],'(PRODUCTS)'!B:B,'(PRODUCTS)'!F:F,"") -> 20 | I9: 35 | J9: 32.65 | K9: 42.4 | L9: 0.15
A10: 17003 | B10: 1/5/2023 | C10: HANAR | D10: =_xlfn.XLOOKUP(_9EXPERT_VLOOKUP_9EXPERT_ORDERS[[#This Row],[CustomerID]],'(CUSTOMERS)'!A:A,'(CUSTOMERS)'!B:B,"") -> Hanari Carnes | E10: =_xlfn.XLOOKUP(_9EXPERT_VLOOKUP_9EXPERT_ORDERS[[#This Row],[Customer]],'(CUSTOMERS)'!B:B,'(CUSTOMERS)'!G:G,"") -> (21) 555-0091 | F10: 8-141 | G10: =_xlfn.XLOOKUP(_9EXPERT_VLOOKUP_9EXPERT_ORDERS[[#This Row],[ProductID]],'(PRODUCTS)'!A:A,'(PRODUCTS)'!B:B,"") -> Jack's New England Clam | H10: =_xlfn.XLOOKUP(_9EXPERT_VLOOKUP_9EXPERT_ORDERS[[#This Row],[Product]],'(PRODUCTS)'!B:B,'(PRODUCTS)'!F:F,"") -> 85 | I10: 10 | J10: 6.43 | K10: 7.7 | L10: 0
A11: 17004 | B11: 1/5/2023 | C11: LEHMS | D11: =_xlfn.XLOOKUP(_9EXPERT_VLOOKUP_9EXPERT_ORDERS[[#This Row],[CustomerID]],'(CUSTOMERS)'!A:A,'(CUSTOMERS)'!B:B,"") -> Lehmanns Marktstand | E11: =_xlfn.XLOOKUP(_9EXPERT_VLOOKUP_9EXPERT_ORDERS[[#This Row],[Customer]],'(CUSTOMERS)'!B:B,'(CUSTOMERS)'!G:G,"") -> 069-0245984 | F11: 5-174 | G11: =_xlfn.XLOOKUP(_9EXPERT_VLOOKUP_9EXPERT_ORDERS[[#This Row],[ProductID]],'(PRODUCTS)'!A:A,'(PRODUCTS)'!B:B,"") -> Filo Mix | H11: =_xlfn.XLOOKUP(_9EXPERT_VLOOKUP_9EXPERT_ORDERS[[#This Row],[Product]],'(PRODUCTS)'!B:B,'(PRODUCTS)'!F:F,"") -> 38 | I11: 146 | J11: 4.26 | K11: 7 | L11: 0.1
A12: 17005 | B12: 1/5/2023 | C12: VICTE | D12: =_xlfn.XLOOKUP(_9EXPERT_VLOOKUP_9EXPERT_ORDERS[[#This Row],[CustomerID]],'(CUSTOMERS)'!A:A,'(CUSTOMERS)'!B:B,"") -> Victuailles en stock | E12: =_xlfn.XLOOKUP(_9EXPERT_VLOOKUP_9EXPERT_ORDERS[[#This Row],[Customer]],'(CUSTOMERS)'!B:B,'(CUSTOMERS)'!G:G,"") -> 78.32.54.86 | F12: 2-125 | G12: =_xlfn.XLOOKUP(_9EXPERT_VLOOKUP_9EXPERT_ORDERS[[#This Row],[ProductID]],'(PRODUCTS)'!A:A,'(PRODUCTS)'!B:B,"") -> Louisiana Fiery Hot Pepper Sauce | H12: =_xlfn.XLOOKUP(_9EXPERT_VLOOKUP_9EXPERT_ORDERS[[#This Row],[Product]],'(PRODUCTS)'!B:B,'(PRODUCTS)'!F:F,"") -> 76 | I12: 20 | J12: 10.44 | K12: 16.8 | L12: 0
A13: 17005 | B13: 1/5/2023 | C13: VICTE | D13: =_xlfn.XLOOKUP(_9EXPERT_VLOOKUP_9EXPERT_ORDERS[[#This Row],[CustomerID]],'(CUSTOMERS)'!A:A,'(CUSTOMERS)'!B:B,"") -> Victuailles en stock | E13: =_xlfn.XLOOKUP(_9EXPERT_VLOOKUP_9EXPERT_ORDERS[[#This Row],[Customer]],'(CUSTOMERS)'!B:B,'(CUSTOMERS)'!G:G,"") -> 78.32.54.86 | F13: 5-102 | G13: =_xlfn.XLOOKUP(_9EXPERT_VLOOKUP_9EXPERT_ORDERS[[#This Row],[ProductID]],'(PRODUCTS)'!A:A,'(PRODUCTS)'!B:B,"") -> Ravioli Angelo | H13: =_xlfn.XLOOKUP(_9EXPERT_VLOOKUP_9EXPERT_ORDERS[[#This Row],[Product]],'(PRODUCTS)'!B:B,'(PRODUCTS)'!F:F,"") -> 36 | I13: 15 | J13: 10.88 | K13: 15.6 | L13: 0.05
... A29: 17010 | B29: 1/9/2023 | C29: RICSU | D29: =_xlfn.XLOOKUP(_9EXPERT_VLOOKUP_9EXPERT_ORDERS[[#This Row],[CustomerID]],'(CUSTOMERS)'!A:A,'(CUSTOMERS)'!B:B,"") -> Richter Supermarkt | E29: =_xlfn.XLOOKUP(_9EXPERT_VLOOKUP_9EXPERT_ORDERS[[#This Row],[Customer]],'(CUSTOMERS)'!B:B,'(CUSTOMERS)'!G:G,"") -> 0897-034214 | F29: 8-120 | G29: =_xlfn.XLOOKUP(_9EXPERT_VLOOKUP_9EXPERT_ORDERS[[#This Row],[ProductID]],'(PRODUCTS)'!A:A,'(PRODUCTS)'!B:B,"") -> Inlagd Sill | H29: =_xlfn.XLOOKUP(_9EXPERT_VLOOKUP_9EXPERT_ORDERS[[#This Row],[Product]],'(PRODUCTS)'!B:B,'(PRODUCTS)'!F:F,"") -> 112 | I29: 25 | J29: 11.86 | K29: 15.2 | L29: 0

Sheet (CUSTOMERS)
A1: Column1 | B1: Column2 | C1: Column3 | D1: Column4 | E1: Column5 | F1: Column6 | G1: Column7
A2: CustomerID | B2: CompanyName | C2: ContactName | D2: ContactTitle | E2: City | F2: Country | G2: Phone
A3: 9EXPERT | B3: 9Expert Co., Ltd. | C3: Natnaree | D3: Sales Representative | E3: Ratchatawi | F3: Thailand | G3: 022194304
A4: ANATR | B4: Ana Trujillo Emparedados y helados | C4: Ana Trujillo | D4: Owner | E4: M้xico D.F. | F4: Mexico | G4: (5) 555-4729
A5: ANTON | B5: Antonio Moreno Taquerํa | C5: Antonio Moreno | D5: Owner | E5: M้xico D.F. | F5: Mexico | G5: (5) 555-3932
A6: AROUT | B6: Around the Horn | C6: Thomas Hardy | D6: Sales Representative | E6: London | F6: UK | G6: (171) 555-7788
A7: ASIAS | B7: Asian Seafoods PLC. | C7: Sirirat Sriwarunyu | D7: Sales Manager | E7: Nonthaburi | F7: Thailand | G7: (662) 589-2137
A8: BERGS | B8: Berglunds snabbk๖p | C8: Christina Berglund | D8: Order Administrator | E8: Luleๅ | F8: Sweden | G8: 0921-12 34 65
A9: BLAUS | B9: Blauer See Delikatessen | C9: Hanna Moos | D9: Sales Representative | E9: Mannheim | F9: Germany | G9: 0621-08460
A10: BLONP | B10: Blondel p่re et fils | C10: Fr้d้rique Citeaux | D10: Marketing Manager | E10: Strasbourg | F10: France | G10: 88.60.15.31
A11: BOLID | B11: B๓lido Comidas preparadas | C11: Martํn Sommer | D11: Owner | E11: Madrid | F11: Spain | G11: (91) 555 22 82
A12: BONAP | B12: Bon app' | C12: Laurence Lebihan | D12: Owner | E12: Marseille | F12: France | G12: 91.24.45.40
... A99: YANWA | B99: Yan Wal Yun | C99: Chaiyong Jitthai | D99: Sales Representative | E99: Rayong | F99: Thailand | G99: (6638) 650-229

Sheet (PRODUCTS)
A1: Product Code | B1: Product | C1: SupplierID | D1: Cost | E1: UnitPrice | F1: UnitsInStock | G1: ReorderLevel | H1: Discontinued
A2: 1-101 | B2: Chai | C2: 4 | D2: 16.54 | E2: 18 | F2: 39 | G2: 10 | H2: FALSE
A3: 1-105 | B3: Chang | C3: 1 | D3: 14.25 | E3: 19 | F3: 17 | G3: 25 | H3: FALSE
A4: 1-106 | B4: Guaran Fantastica | C4: 10 | D4: 3.32 | E4: 4.5 | F4: 20 | G4: 0 | H4: TRUE
A5: 1-108 | B5: Lakkalikri | C5: 23 | D5: 14.54 | E5: 18 | F5: 57 | G5: 20 | H5: FALSE
A6: 1-121 | B6: Rhnbru Klosterbier | C6: 12 | D6: 5.92 | E6: 7.75 | F6: 125 | G6: 25 | H6: FALSE
A7: 1-129 | B7: Outback Lager | C7: 7 | D7: 12.51 | E7: 15 | F7: 15 | G7: 30 | H7: FALSE
A8: 1-132 | B8: Laughing Lumberjack Lager | C8: 16 | D8: 10.6 | E8: 14 | F8: 52 | G8: 10 | H8: FALSE
A9: 1-136 | B9: C๔tes de Blaye | C9: 18 | D9: 166.5 | E9: 185 | F9: 17 | G9: 15 | H9: FALSE
A10: 1-140 | B10: Sasquatch Ale | C10: 16 | D10: 12.85 | E10: 14 | F10: 111 | G10: 15 | H10: FALSE
A11: 1-189 | B11: Steeleye Stout | C11: 16 | D11: 14.06 | E11: 18 | F11: 20 | G11: 15 | H11: FALSE
A12: 1-190 | B12: Ipoh Coffee | C12: 20 | D12: 43.56 | E12: 46 | F12: 17 | G12: 25 | H12: FALSE
A13: 1-196 | B13: Chartreuse verte | C13: 18 | D13: 15.73 | E13: 18 | F13: 69 | G13: 5 | H13: FALSE
... A78: 8-194 | B78: Spegesild | C78: 21 | D78: 9.74 | E78: 12 | F78: 95 | G78: 0 | H78: FALSE

Sheet Sheet1
B1: Jan | C1: Fed | D1: mar | E1: Apr | F1: May | G1: June | H1: July | I1: Aug | J1: Sept | K1: Oct | L1: Nov | M1: Dec
A2: Revenue | B2: 180000 | C2: 185000 | D2: 195000 | E2: 210000 | F2: 200000 | G2: 205000 | H2: 210000 | I2: 215000 | J2: 205000 | K2: 220000 | L2: 230000 | M2: 250000
A3: Cost | B3: 130000 | C3: 132000 | D3: 135000 | E3: 140000 | F3: 138000 | G3: 140000 | H3: 145000 | I3: 145000 | J3: 140000 | K3: 145000 | L3: 150000 | M3: 560000

Sheet Sheet2
A1: Dashboard
A3: เดือน | B3: Jan
A4: รายได้ | B4: =_xlfn.XLOOKUP(Sheet2!B3,Sheet1!1:1,Sheet1!2:2) -> 180000
A5: รายจ่าย | B5: =_xlfn.XLOOKUP(B3,Sheet1!1:1,Sheet1!3:3) -> 130000
